tencheck/__init__.py
tencheck/checks.py
tencheck/examples.py
tencheck/harness.py
tencheck/input.py
tencheck/loss.py
tencheck/py.typed
tencheck/torchviz.py
tencheck/type.py
tencheck-0.0.4.dist-info/LICENSE
tencheck-0.0.4.dist-info/METADATA
tencheck-0.0.4.dist-info/WHEEL
tencheck-0.0.4.dist-info/top_level.txt
tencheck-0.0.4.dist-info/RECORD
