Metadata-Version: 2.1
Name: tencheck
Version: 0.0.4
Summary: A library for pytorch layer testing.
Author-email: Justin Yan <justin@iomorphic.com>
Project-URL: Homepage, https://github.com/justin-yan/tencheck
Classifier: Intended Audience :: Developers
Classifier: Operating System :: OS Independent
Classifier: License :: OSI Approved :: MIT License
Classifier: Programming Language :: Python
Classifier: Programming Language :: Python :: 3
Classifier: Programming Language :: Python :: 3.11
Requires-Python: >=3.11
License-File: LICENSE
Requires-Dist: torch <2.4,>2
Requires-Dist: jaxtyping
Requires-Dist: numpy
Requires-Dist: graphviz
